autotrace/__init__.py
autotrace/autotrace.py
autotrace-0.0.26.dist-info/DESCRIPTION.rst
autotrace-0.0.26.dist-info/METADATA
autotrace-0.0.26.dist-info/RECORD
autotrace-0.0.26.dist-info/WHEEL
autotrace-0.0.26.dist-info/entry_points.txt
autotrace-0.0.26.dist-info/metadata.json
autotrace-0.0.26.dist-info/top_level.txt
