Metadata-Version: 2.0
Name: autotrace
Version: 0.0.26
Summary: Trace a command in real time
Home-page: UNKNOWN
Author: Ian Miell
Author-email: ian.miell@gmail.com
License: UNKNOWN
Platform: UNKNOWN
Requires-Dist: curtsies
Requires-Dist: pexpect
Requires-Dist: dateparser
